monopyly/CHANGELOG.md
monopyly/README.md
monopyly/__init__.py
monopyly/_version.py
monopyly/auth/actions.py
monopyly/auth/blueprint.py
monopyly/auth/routes.py
monopyly/auth/tools.py
monopyly/banking/accounts.py
monopyly/banking/actions.py
monopyly/banking/banks.py
monopyly/banking/blueprint.py
monopyly/banking/filters.py
monopyly/banking/forms.py
monopyly/banking/routes.py
monopyly/banking/transactions.py
monopyly/common/transactions.py
monopyly/common/utils.py
monopyly/common/forms/__init__.py
monopyly/common/forms/_forms.py
monopyly/common/forms/fields.py
monopyly/common/forms/utils.py
monopyly/common/forms/validators.py
monopyly/core/actions.py
monopyly/core/blueprint.py
monopyly/core/context_processors.py
monopyly/core/errors.py
monopyly/core/filters.py
monopyly/core/internal_transactions.py
monopyly/core/routes.py
monopyly/credit/accounts.py
monopyly/credit/actions.py
monopyly/credit/blueprint.py
monopyly/credit/cards.py
monopyly/credit/forms.py
monopyly/credit/routes.py
monopyly/credit/statements.py
monopyly/credit/transactions/__init__.py
monopyly/credit/transactions/_transactions.py
monopyly/credit/transactions/activity/__init__.py
monopyly/credit/transactions/activity/data.py
monopyly/credit/transactions/activity/parser.py
monopyly/credit/transactions/activity/reconciliation.py
monopyly/database/__init__.py
monopyly/database/models.py
monopyly/database/preloads.sql
monopyly/database/schema.sql
monopyly/database/views.sql
monopyly/scripts/screenshot_application.py
monopyly/static/chartist-1.5.0.min.js
monopyly/static/jquery-3.7.1.min.js
monopyly/static/css/style.css
monopyly/static/favicon/browserconfig.xml
monopyly/static/favicon/favicon-114.png
monopyly/static/favicon/favicon-120.png
monopyly/static/favicon/favicon-144.png
monopyly/static/favicon/favicon-150.png
monopyly/static/favicon/favicon-152.png
monopyly/static/favicon/favicon-16.png
monopyly/static/favicon/favicon-160.png
monopyly/static/favicon/favicon-180.png
monopyly-1.6.1.dist-info/METADATA
monopyly-1.6.1.dist-info/WHEEL
monopyly-1.6.1.dist-info/entry_points.txt
monopyly-1.6.1.dist-info/licenses/COPYING
monopyly-1.6.1.dist-info/licenses/LICENSE
monopyly-1.6.1.dist-info/RECORD
