Metadata-Version: 2.4
Name: monopyly
Version: 1.6.1
Summary: A homemade personal finance manager.
Project-URL: Download, https://pypi.org/project/monopyly
Project-URL: Homepage, http://monopyly.com
Project-URL: Repository, https://github.com/mitchnegus/monopyly
Project-URL: Changelog, https://github.com/mitchnegus/monopyly/blob/main/CHANGELOG.md
Author-email: Mitch Negus <mitchnegus57@gmail.com>
License: GNU GPLv3
License-File: COPYING
License-File: LICENSE
Keywords: Finance,Personal Finance
Classifier: Development Status :: 3 - Alpha
Classifier: Environment :: Web Environment
Classifier: Framework :: Flask
Classifier: Intended Audience :: End Users/Desktop
Classifier: License :: OSI Approved :: GNU General Public License v3 (GPLv3)
Classifier: Natural Language :: English
Classifier: Operating System :: OS Independent
Classifier: Programming Language :: Python
Classifier: Topic :: Office/Business :: Financial
Classifier: Topic :: Office/Business :: Financial :: Accounting
Classifier: Topic :: Office/Business :: Financial :: Spreadsheet
Requires-Python: >=3.10
Requires-Dist: dry-foundation==1.6.0
Requires-Dist: flask-wtf==1.2.2
Requires-Dist: flask==3.1.2
Requires-Dist: gunicorn==23.0.0
Requires-Dist: markdown==3.10
Requires-Dist: nltk==3.9.2
Requires-Dist: python-dateutil==2.9.0
Requires-Dist: rich==14.2.0
Requires-Dist: sqlalchemy==2.0.45
